desencriptar_modulo/__init__.py
desencriptar_modulo/desencriptar.py
GC_DESENCRIP_TEM-1.0.0.dist-info/LICENSE
GC_DESENCRIP_TEM-1.0.0.dist-info/METADATA
GC_DESENCRIP_TEM-1.0.0.dist-info/WHEEL
GC_DESENCRIP_TEM-1.0.0.dist-info/top_level.txt
GC_DESENCRIP_TEM-1.0.0.dist-info/RECORD
