Metadata-Version: 2.1
Name: GC-DESENCRIP-TEM
Version: 1.0.0
Summary: Módulo para desencriptar archivos .crp utilizando AES y Secrets Manager
Author: GCardenas
Author-email: tuemail@ejemplo.com
Classifier: Programming Language :: Python :: 3
Classifier: License :: OSI Approved :: MIT License
Classifier: Operating System :: OS Independent
Requires-Python: >=3.6
License-File: LICENSE
Requires-Dist: boto3
Requires-Dist: pycryptodome
